kg_flask_crud/__init__.py
kg_flask_crud-0.0.5.dist-info/METADATA
kg_flask_crud-0.0.5.dist-info/WHEEL
kg_flask_crud-0.0.5.dist-info/top_level.txt
kg_flask_crud-0.0.5.dist-info/RECORD
